[{

  "idSeguro": 1,

  "nif": "12345678Z",

  "nombre": "Carlos",

  "ape1": "Cano",

  "edad": 41,

  "sexo": "H",

  "casado": true,

  "numHijos": 3,

  "embarazada": false,

  "coberturas": {

    "oftalmologia": true,

    "dental": false,

    "fecundacionInVitro": false

  },

  "enfermedades": {

    "corazon": true,

    "estomacal": false,

    "rinyones": false,

    "alergia": true,

    "nombreAlergia": "Acaros"

  }

}, {

  "idSeguro": 2,

  "nif": "34783627Z",

  "nombre": "Catalina",

  "ape1": "López",

  "edad": 33,

  "sexo": "M",

  "casado": true,

  "numHijos": 1,

  "embarazada": true,

  "coberturas": {

    "oftalmologia": false,

    "dental": false,

    "fecundacionInVitro": false

  },

  "enfermedades": {

    "corazon": false,

    "estomacal": false,

    "rinyones": false,

    "alergia": false,

    "nombreAlergia": ""

  }

}, {

  "idSeguro": 3,

  "nif": "29069345J",

  "nombre": "Jose",

  "ape1": "Aguado",

  "edad": 56,

  "sexo": "H",

  "casado": true,

  "numHijos": 2,

  "embarazada": false,

  "coberturas": {

    "oftalmologia": true,

    "dental": true,

    "fecundacionInVitro": false

  },

  "enfermedades": {

    "corazon": true,

    "estomacal": true,

    "rinyones": true,

    "alergia": false,

    "nombreAlergia": ""

  }

}, {

  "idSeguro": 4,

  "nif": "34828938S",

  "nombre": "Angel",

  "ape1": "Navarro",

  "edad": 21,

  "sexo": "H",

  "casado": false,

  "numHijos": 0,

  "embarazada": false,

  "coberturas": {

    "oftalmologia": true,

    "dental": true,

    "fecundacionInVitro": false

  },

  "enfermedades": {

    "corazon": false,

    "estomacal": false,

    "rinyones": false,

    "alergia": true,

    "nombreAlergia": "Graminias"

  }

}, {

  "idSeguro": 5,

  "nif": "23236773B",

  "nombre": "Teresa",

  "ape1": "Rubio",

  "edad": 36,

  "sexo": "M",

  "casado": false,

  "numHijos": 0,

  "embarazada": true,

  "coberturas": {

    "oftalmologia": false,

    "dental": false,

    "fecundacionInVitro": true

  },

  "enfermedades": {

    "corazon": false,

    "estomacal": false,

    "rinyones": false,

    "alergia": false,

    "nombreAlergia": ""

  }

}, {

  "idSeguro": 6,

  "nif": "27469252F",

  "nombre": "Alfredo",

  "ape1": "Padilla",

  "edad": 45,

  "sexo": "H",

  "casado": true,

  "numHijos": 2,

  "embarazada": false,

  "coberturas": {

    "oftalmologia": true,

    "dental": true,

    "fecundacionInVitro": false

  },

  "enfermedades": {

    "corazon": true,

    "estomacal": false,

    "rinyones": false,

    "alergia": false,

    "nombreAlergia": ""

  }

}, {

  "idSeguro": 7,

  "nif": "34804406R",

  "nombre": "Rosa",

  "ape1": "Muñoz",

  "edad": 45,

  "sexo": "M",

  "casado": true,

  "numHijos": 3,

  "embarazada": false,

  "coberturas": {

    "oftalmologia": false,

    "dental": false,

    "fecundacionInVitro": false

  },

  "enfermedades": {

    "corazon": false,

    "estomacal": false,

    "rinyones": false,

    "alergia": false,

    "nombreAlergia": ""

  }

}, {

  "idSeguro": 8,

  "nif": "23244114S",

  "nombre": "Alejandro",

  "ape1": "Valeno",

  "edad": 19,

  "sexo": "H",

  "casado": false,

  "numHijos": 0,

  "embarazada": false,

  "coberturas": {

    "oftalmologia": true,

    "dental": false,

    "fecundacionInVitro": false

  },

  "enfermedades": {

    "corazon": false,

    "estomacal": false,

    "rinyones": false,

    "alergia": true,

    "nombreAlergia": "Leche"

  }

}]

